README.rst
setup.py
biomartpy/__init__.py
biomartpy.egg-info/PKG-INFO
biomartpy.egg-info/SOURCES.txt
biomartpy.egg-info/dependency_links.txt
biomartpy.egg-info/requires.txt
biomartpy.egg-info/top_level.txt