Metadata-Version: 1.1
Name: biomartpy
Version: 0.1.1
Summary: 
